toSpcy/__init__.py
toSpcy/toSpacy.py
toSpcy-1.0.0.dist-info/LICENSE.txt
toSpcy-1.0.0.dist-info/METADATA
toSpcy-1.0.0.dist-info/WHEEL
toSpcy-1.0.0.dist-info/top_level.txt
toSpcy-1.0.0.dist-info/RECORD
